scralenium/__init__.py
scralenium/__version__.py
scralenium/http.py
scralenium/middlewares.py
scralenium-0.1.3.dist-info/LICENSE
scralenium-0.1.3.dist-info/METADATA
scralenium-0.1.3.dist-info/WHEEL
scralenium-0.1.3.dist-info/top_level.txt
scralenium-0.1.3.dist-info/RECORD
