Metadata-Version: 2.1
Name: scralenium
Version: 0.1.3
Summary: Middleware for scrapy using selenium webdriver.
Home-page: https://github.com/alexpdev/scralenium
Author: alexpdev
Author-email: alexpdev <alexpdev@pm.me>
License: Apache Software License
Keywords: scrapy,selenium,web-scraping
Classifier: Development Status :: 4 - Beta
Classifier: Intended Audience :: Developers
Classifier: License :: OSI Approved :: Apache Software License
Classifier: Operating System :: OS Independent
Classifier: Programming Language :: Python :: 3.5
Classifier: Programming Language :: Python :: 3.6
Classifier: Programming Language :: Python :: 3.7
Classifier: Programming Language :: Python :: 3.8
Classifier: Programming Language :: Python :: 3.9
Classifier: Programming Language :: Python :: 3.10
Classifier: Programming Language :: Python :: 3.11
License-File: LICENSE
Requires-Dist: scrapy
Requires-Dist: selenium
